{
  "item_boots": { "name": "速度之靴", "category": "tempo" },
  "item_phase_boots": { "name": "相位鞋", "category": "tempo" },
  "item_power_treads": { "name": "动力鞋", "category": "tempo" },
  "item_tranquil_boots": { "name": "静谧之鞋", "category": "tempo" },
  "item_arcane_boots": { "name": "奥术鞋", "category": "tempo" },
  "item_travel_boots": { "name": "远行鞋", "category": "tempo" },
  "item_magic_wand": { "name": "魔棒", "category": "lane" },
  "item_bracer": { "name": "护腕", "category": "lane" },
  "item_wraith_band": { "name": "怨灵系带", "category": "lane" },
  "item_null_talisman": { "name": "空灵挂件", "category": "lane" },
  "item_hand_of_midas": { "name": "迈达斯之手", "category": "farm" },
  "item_bfury": { "name": "狂战斧", "category": "farm" },
  "item_maelstrom": { "name": "漩涡", "category": "farm" },
  "item_mjollnir": { "name": "雷神之锤", "category": "damage" },
  "item_radiance": { "name": "辉耀", "category": "farm" },
  "item_echo_sabre": { "name": "回音战刃", "category": "damage" },
  "item_harpoon": { "name": "鱼叉", "category": "control" },
  "item_armlet": { "name": "莫尔迪基安的臂章", "category": "damage" },
  "item_sange_and_yasha": { "name": "散夜对剑", "category": "survival" },
  "item_yasha_and_kaya": { "name": "散慧对剑", "category": "damage" },
  "item_manta": { "name": "幻影斧", "category": "survival" },
  "item_black_king_bar": { "name": "黑皇杖", "category": "survival" },
  "item_butterfly": { "name": "蝴蝶", "category": "damage" },
  "item_skadi": { "name": "斯嘉蒂之眼", "category": "survival" },
  "item_abyssal_blade": { "name": "深渊之刃", "category": "control" },
  "item_basher": { "name": "碎颅锤", "category": "control" },
  "item_blink": { "name": "闪烁匕首", "category": "mobility" },
  "item_overwhelming_blink": { "name": "盛势闪光", "category": "mobility" },
  "item_swift_blink": { "name": "迅疾闪光", "category": "mobility" },
  "item_arcane_blink": { "name": "秘奥闪光", "category": "mobility" },
  "item_force_staff": { "name": "原力法杖", "category": "save" },
  "item_glimmer_cape": { "name": "微光披风", "category": "save" },
  "item_ultimate_scepter": { "name": "阿哈利姆神杖", "category": "utility" },
  "item_ultimate_scepter_2": { "name": "阿哈利姆魔晶", "category": "utility" },
  "item_aether_lens": { "name": "以太之镜", "category": "utility" },
  "item_hurricane_pike": { "name": "飓风长戟", "category": "save" },
  "item_dragon_lance": { "name": "魔龙枪", "category": "damage" },
  "item_desolator": { "name": "黯灭", "category": "damage" },
  "item_satanic": { "name": "撒旦之邪力", "category": "survival" },
  "item_sphere": { "name": "林肯法球", "category": "survival" },
  "item_silver_edge": { "name": "白银之锋", "category": "counter" },
  "item_invis_sword": { "name": "影刃", "category": "mobility" },
  "item_monkey_king_bar": { "name": "金箍棒", "category": "counter" },
  "item_shivas_guard": { "name": "希瓦的守护", "category": "armor" },
  "item_pipe": { "name": "洞察烟斗", "category": "team" },
  "item_lotus_orb": { "name": "清莲宝珠", "category": "save" },
  "item_spirit_vessel": { "name": "魂之灵瓮", "category": "counter" },
  "item_guardian_greaves": { "name": "卫士胫甲", "category": "team" },
  "item_mekansm": { "name": "梅肯斯姆", "category": "team" },
  "item_crimson_guard": { "name": "赤红甲", "category": "team" },
  "item_assault": { "name": "强袭胸甲", "category": "armor" },
  "item_orchid": { "name": "紫怨", "category": "control" },
  "item_bloodthorn": { "name": "血棘", "category": "control" },
  "item_sheepstick": { "name": "邪恶镰刀", "category": "control" },
  "item_cyclone": { "name": "Eul的神圣法杖", "category": "save" },
  "item_wind_waker": { "name": "风之杖", "category": "save" },
  "item_ghost": { "name": "幽魂权杖", "category": "save" },
  "item_ethereal_blade": { "name": "虚灵之刃", "category": "save" },
  "item_blade_mail": { "name": "刃甲", "category": "survival" },
  "item_vanguard": { "name": "先锋盾", "category": "survival" },
  "item_heart": { "name": "恐鳌之心", "category": "survival" },
  "item_refresher": { "name": "刷新球", "category": "utility" },
  "item_heavens_halberd": { "name": "天堂之戟", "category": "counter" },
  "item_gem": { "name": "真视宝石", "category": "vision" },
  "item_dust": { "name": "显影之尘", "category": "vision" },
  "item_ward_dispenser": { "name": "侦查/岗哨守卫", "category": "vision" }
}
